databear/__init__.py
databear/databearCLI.py
databear/databearDB.py
databear/databearDB.sql
databear/errors.py
databear/logger.py
databear/measure.py
databear/process.py
databear/schedule.py
databear/sensor.py
databear/sensorfactory.py
databear/drivers/__init__.py
databear/drivers/dbdriver.py
databear/drivers/windriver.py
databear/sensors/__init__.py
databear/sensors/databearSim.py
databear/sensors/databearSimStream.py
databear/sensors/dyacon.py
databear/sensors/dyaconTPH1.py
databear/sensors/dyaconTPH1B.py
databear/sensors/dyaconTPH1C.py
databear/sensors/dyaconWSD2.py
databear/sensors/generalsensors.py
databear/sensors/gill.py
databear/sensors/gillTest.py
databear/sensors/sensor.py
databear/sensors/sensorbus.py
databear/sensors/sensorfactory.py
databear/sensors/simStream.py
databear-2.2.dist-info/LICENSE
databear-2.2.dist-info/METADATA
databear-2.2.dist-info/WHEEL
databear-2.2.dist-info/entry_points.txt
databear-2.2.dist-info/top_level.txt
databear-2.2.dist-info/RECORD
