Metadata-Version: 2.1
Name: databear
Version: 2.2
Summary: A Python based data logger
Home-page: https://github.com/chrisrycx/DataBear
Author: Chris Cox
Author-email: chrisrycx@gmail.com
License: UNKNOWN
Platform: UNKNOWN
Classifier: Programming Language :: Python :: 3
Classifier: License :: OSI Approved :: MIT License
Classifier: Operating System :: OS Independent
Requires-Python: >=3.6
Requires-Dist: pyyaml
Requires-Dist: numpy
